osu_wiki_tools-2.4.1.dist-info/licenses/LICENCE.md
wikitools/__init__.py
wikitools/article_parser.py
wikitools/code_block_parser.py
wikitools/comment_parser.py
wikitools/console.py
wikitools/errors.py
wikitools/file_utils.py
wikitools/git_utils.py
wikitools/identifier_parser.py
wikitools/link_checker.py
wikitools/link_parser.py
wikitools/redirect_parser.py
wikitools/reference_parser.py
wikitools/yaml_rules.py
wikitools_cli/VERSION.py
wikitools_cli/__init__.py
wikitools_cli/osu_wiki_tools.py
wikitools_cli/update_tournament_countries.py
wikitools_cli/commands/__init__.py
wikitools_cli/commands/check_files.py
wikitools_cli/commands/check_links.py
wikitools_cli/commands/check_outdated_articles.py
wikitools_cli/commands/check_yaml.py
osu_wiki_tools-2.4.1.dist-info/METADATA
osu_wiki_tools-2.4.1.dist-info/WHEEL
osu_wiki_tools-2.4.1.dist-info/entry_points.txt
osu_wiki_tools-2.4.1.dist-info/top_level.txt
osu_wiki_tools-2.4.1.dist-info/RECORD
