Metadata-Version: 2.4
Name: osu-wiki-tools
Version: 2.4.1
Summary: Various tools for osu! wiki contributors
Home-page: https://github.com/Walavouchey/osu-wiki-tools
Author: Walavouchey
Author-email: wala@yui.tv
Project-URL: Bug Tracker, https://github.com/Walavouchey/osu-wiki-tools/issues
Classifier: Programming Language :: Python :: 3
Classifier: License :: OSI Approved :: MIT License
Classifier: Operating System :: OS Independent
Requires-Python: >=3.11
License-File: LICENCE.md
Requires-Dist: PyYAML==6.0.1
Requires-Dist: types-PyYAML==6.0.12.12
Requires-Dist: yamllint==1.33.0
Requires-Dist: braceexpand==0.1.7
Dynamic: author
Dynamic: author-email
Dynamic: classifier
Dynamic: description
Dynamic: description-content-type
Dynamic: home-page
Dynamic: license-file
Dynamic: project-url
Dynamic: requires-dist
Dynamic: requires-python
Dynamic: summary
